mitmproxy/__init__.py
mitmproxy/addonmanager.py
mitmproxy/certs.py
mitmproxy/command.py
mitmproxy/command_lexer.py
mitmproxy/connection.py
mitmproxy/ctx.py
mitmproxy/dns.py
mitmproxy/eventsequence.py
mitmproxy/exceptions.py
mitmproxy/flow.py
mitmproxy/flowfilter.py
mitmproxy/hooks.py
mitmproxy/http.py
mitmproxy/log.py
mitmproxy/master.py
mitmproxy/options.py
mitmproxy/optmanager.py
mitmproxy/py.typed
mitmproxy/tcp.py
mitmproxy/tls.py
mitmproxy/types.py
mitmproxy/udp.py
mitmproxy/version.py
mitmproxy/websocket.py
mitmproxy/addons/__init__.py
mitmproxy/addons/anticache.py
mitmproxy/addons/anticomp.py
mitmproxy/addons/asgiapp.py
mitmproxy/addons/block.py
mitmproxy/addons/blocklist.py
mitmproxy/addons/browser.py
mitmproxy/addons/clientplayback.py
mitmproxy/addons/command_history.py
mitmproxy/addons/comment.py
mitmproxy/addons/core.py
mitmproxy/addons/cut.py
mitmproxy/addons/disable_h2c.py
mitmproxy/addons/dns_resolver.py
mitmproxy/addons/dumper.py
mitmproxy/addons/errorcheck.py
mitmproxy/addons/eventstore.py
mitmproxy/addons/export.py
mitmproxy/addons/intercept.py
mitmproxy/addons/keepserving.py
mitmproxy/addons/maplocal.py
mitmproxy/addons/mapremote.py
mitmproxy/addons/modifybody.py
mitmproxy/addons/modifyheaders.py
mitmproxy/addons/next_layer.py
mitmproxy/addons/onboarding.py
mitmproxy/addons/proxyauth.py
mitmproxy/addons/proxyserver.py
mitmproxy/addons/readfile.py
mitmproxy/addons/save.py
mitmproxy/addons/savehar.py
mitmproxy/addons/script.py
mitmproxy/addons/server_side_events.py
mitmproxy/addons/serverplayback.py
mitmproxy/addons/stickyauth.py
mitmproxy/addons/stickycookie.py
mitmproxy/addons/strip_dns_https_records.py
mitmproxy/addons/termlog.py
mitmproxy/addons/tlsconfig.py
mitmproxy/addons/update_alt_svc.py
mitmproxy/addons/upstream_auth.py
mitmproxy/addons/view.py
mitmproxy/addons/onboardingapp/__init__.py
mitmproxy/addons/onboardingapp/static/bootstrap.min.css
mitmproxy/addons/onboardingapp/static/mitmproxy.css
mitmproxy-12.1.0.dist-info/LICENSE
mitmproxy-12.1.0.dist-info/METADATA
mitmproxy-12.1.0.dist-info/WHEEL
mitmproxy-12.1.0.dist-info/entry_points.txt
mitmproxy-12.1.0.dist-info/top_level.txt
mitmproxy-12.1.0.dist-info/RECORD
