Metadata-Version: 2.1
Name: mitmproxy
Version: 12.1.0
Summary: An interactive, SSL/TLS-capable intercepting proxy for HTTP/1, HTTP/2, and WebSockets.
Author-email: Aldo Cortesi <aldo@corte.si>
Maintainer-email: Maximilian Hils <mitmproxy@maximilianhils.com>
License: Copyright (c) 2013, Aldo Cortesi. All rights reserved.
Project-URL: Homepage, https://mitmproxy.org
Project-URL: Source, https://github.com/mitmproxy/mitmproxy/
Project-URL: Documentation, https://docs.mitmproxy.org/stable/
Project-URL: Issues, https://github.com/mitmproxy/mitmproxy/issues
Classifier: License :: OSI Approved :: MIT License
Classifier: Development Status :: 5 - Production/Stable
Classifier: Environment :: Console :: Curses
Classifier: Operating System :: MacOS
Classifier: Operating System :: POSIX
Classifier: Operating System :: Microsoft :: Windows
Classifier: Programming Language :: Python :: 3 :: Only
Classifier: Programming Language :: Python :: 3.12
Classifier: Programming Language :: Python :: 3.13
Classifier: Programming Language :: Python :: Implementation :: CPython
Classifier: Topic :: Security
Classifier: Topic :: Internet :: WWW/HTTP
Classifier: Topic :: Internet :: Proxy Servers
Classifier: Topic :: System :: Networking :: Monitoring
Classifier: Topic :: Software Development :: Testing
Classifier: Typing :: Typed
Requires-Python: >=3.12
License-File: LICENSE
Requires-Dist: aioquic<=1.2.0,>=1.2.0
Requires-Dist: argon2-cffi<=23.1.0,>=23.1.0
Requires-Dist: asgiref<=3.8.1,>=3.2.10
Requires-Dist: Brotli<=1.1.0,>=1.0
Requires-Dist: certifi>=2019.9.11
Requires-Dist: cryptography<44.1,>=42.0
Requires-Dist: flask<=3.1.0,>=3.0
Requires-Dist: h11<=0.16.0,>=0.16.0
Requires-Dist: h2<=4.1.0,>=4.1
Requires-Dist: hyperframe<=6.1.0,>=6.0
Requires-Dist: kaitaistruct<=0.10,>=0.10
Requires-Dist: ldap3<=2.9.1,>=2.8
Requires-Dist: mitmproxy-rs<0.13,>=0.12.3
Requires-Dist: msgpack<=1.1.0,>=1.0.0
Requires-Dist: passlib<=1.7.4,>=1.6.5
Requires-Dist: pyOpenSSL<=25.0.0,>=24.3
Requires-Dist: pyparsing<=3.2.3,>=2.4.2
Requires-Dist: pyperclip<=1.9.0,>=1.9.0
Requires-Dist: ruamel.yaml<=0.18.10,>=0.18.10
Requires-Dist: sortedcontainers<=2.4.0,>=2.3
Requires-Dist: tornado<=6.5.0,>=6.5.0
Requires-Dist: urwid<=2.6.16,>=2.6.14
Requires-Dist: wsproto<=1.2.0,>=1.0
Requires-Dist: publicsuffix2<=2.20191221,>=2.20190812
Requires-Dist: zstandard<=0.23.0,>=0.15
Requires-Dist: typing-extensions<=4.14,>=4.13.2; python_version < "3.13"
Requires-Dist: pydivert<=2.1.0,>=2.0.3; sys_platform == "win32"
